contrast_vulnerability_metrics/__init__.py
contrast_vulnerability_metrics/__main__.py
contrast_vulnerability_metrics/analyzer.py
contrast_vulnerability_metrics/cli.py
contrast_vulnerability_metrics/config.py
contrast_vulnerability_metrics/exceptions.py
contrast_vulnerability_metrics/models.py
contrast_vulnerability_metrics/resilient.py
contrast_vulnerability_metrics/utils.py
contrast_vulnerability_metrics-0.1.0.dist-info/METADATA
contrast_vulnerability_metrics-0.1.0.dist-info/WHEEL
contrast_vulnerability_metrics-0.1.0.dist-info/entry_points.txt
contrast_vulnerability_metrics-0.1.0.dist-info/licenses/LICENSE
contrast_vulnerability_metrics-0.1.0.dist-info/RECORD
